devicons/__init__.py
devicons-0.1.0.dist-info/WHEEL
devicons-0.1.0.dist-info/METADATA
devicons-0.1.0.dist-info/RECORD
